SpiderKeeper/__init__.py
SpiderKeeper/app/__init__.py
SpiderKeeper/app/config.py
SpiderKeeper/app/blueprints/__init__.py
SpiderKeeper/app/blueprints/dashboard/__init__.py
SpiderKeeper/app/blueprints/dashboard/api.py
SpiderKeeper/app/blueprints/dashboard/model.py
SpiderKeeper/app/blueprints/dashboard/views.py
SpiderKeeper/app/extensions/__init__.py
SpiderKeeper/app/extensions/sqlalchemy.py
SpiderKeeper/app/proxy/__init__.py
SpiderKeeper/app/proxy/spiderctrl.py
SpiderKeeper/app/proxy/contrib/__init__.py
SpiderKeeper/app/proxy/contrib/scrapy.py
SpiderKeeper/app/static/css/AdminLTE.min.css
SpiderKeeper/app/static/css/app.css
SpiderKeeper/app/static/css/bootstrap.min.css
SpiderKeeper/app/static/css/bootstrap.min.css.map
SpiderKeeper/app/static/css/font-awesome.min.css
SpiderKeeper/app/static/css/ionicons.min.css
SpiderKeeper/app/static/css/alt/AdminLTE-without-plugins.min.css
SpiderKeeper/app/static/css/skins/_all-skins.min.css
SpiderKeeper/app/static/css/skins/skin-black-light.min.css
SpiderKeeper/app/static/fonts/FontAwesome.otf
SpiderKeeper/app/static/fonts/fontawesome-webfont.eot
SpiderKeeper/app/static/fonts/fontawesome-webfont.svg
SpiderKeeper/app/static/fonts/fontawesome-webfont.ttf
SpiderKeeper/app/static/fonts/fontawesome-webfont.woff
SpiderKeeper/app/static/fonts/fontawesome-webfont.woff2
SpiderKeeper/app/static/fonts/glyphicons-halflings-regular.eot
SpiderKeeper/app/static/fonts/glyphicons-halflings-regular.svg
SpiderKeeper/app/static/fonts/glyphicons-halflings-regular.ttf
SpiderKeeper/app/static/fonts/glyphicons-halflings-regular.woff
SpiderKeeper/app/static/fonts/glyphicons-halflings-regular.woff2
SpiderKeeper/app/static/fonts/ionicons.eot
SpiderKeeper/app/static/fonts/ionicons.svg
SpiderKeeper/app/static/fonts/ionicons.ttf
SpiderKeeper/app/static/fonts/ionicons.woff
SpiderKeeper/app/static/js/AdminLTE.min.js
SpiderKeeper/app/static/js/Chart.min.js
SpiderKeeper/app/static/js/bootstrap.min.js
SpiderKeeper_2-0.3.2.dist-info/DESCRIPTION.rst
SpiderKeeper_2-0.3.2.dist-info/METADATA
SpiderKeeper_2-0.3.2.dist-info/RECORD
SpiderKeeper_2-0.3.2.dist-info/WHEEL
SpiderKeeper_2-0.3.2.dist-info/entry_points.txt
SpiderKeeper_2-0.3.2.dist-info/metadata.json
SpiderKeeper_2-0.3.2.dist-info/top_level.txt
